{"schemas": {"table_0": {"required": ["birthday", "is_cool", "name", "pets"], "$schema": "http://json-schema.org/schema#", "type": "object", "properties": {"birthday": {"type": "string"}, "name": {"type": "string"}, "pets": {"type": "array", "items": {"required": ["age", "name", "species"], "type": "object", "properties": {"name": {"type": "string"}, "age": {"type": "number"}, "species": {"type": "string"}}}}, "is_cool": {"type": "boolean"}}}}, "previously_seen_files": {"table_0": ["cb6716e02bcfccea625c529b63cd0f5d"]}}
